ingeniictl/CHANGELOG.md
ingeniictl/__init__.py
ingeniictl/__main__.py
ingeniictl/cli/infra/__init__.py
ingeniictl/cli/infra/destroy.py
ingeniictl/cli/infra/disable_resource_protection.py
ingeniictl/cli/infra/main.py
ingeniictl/clients/__init__.py
ingeniictl/clients/logger.py
ingeniictl/clients/pulumi.py
ingeniictl/config.py
ingeniictl/main.py
ingeniictl-0.2.2.dist-info/entry_points.txt
ingeniictl-0.2.2.dist-info/WHEEL
ingeniictl-0.2.2.dist-info/METADATA
ingeniictl-0.2.2.dist-info/RECORD
