Metadata-Version: 2.1
Name: ingeniictl
Version: 0.2.2
Summary: Ingenii's Swiss Army Knife
Author: Teodor Kostadinov
Author-email: teodor@ingenii.dev
Requires-Python: >=3.9,<4.0
Classifier: Programming Language :: Python :: 3
Classifier: Programming Language :: Python :: 3.10
Classifier: Programming Language :: Python :: 3.9
Requires-Dist: typer (>=0.4.0,<0.5.0)
